Metadata-Version: 2.1
Name: oss-internal-tool
Version: 1.7.3
Summary: An internal utility package for Aliyun OSS operations.
Author: Heyu007
Author-email: 610369073@qq.com
License: MIT
Classifier: Programming Language :: Python :: 3
Classifier: Operating System :: OS Independent
Classifier: License :: OSI Approved :: MIT License
Classifier: Intended Audience :: Developers
Classifier: Topic :: Software Development :: Libraries
Requires-Python: >=3.10
License-File: LICENSE
Requires-Dist: aiohappyeyeballs
Requires-Dist: aiohttp
Requires-Dist: aiosignal
Requires-Dist: aliyun-python-sdk-core
Requires-Dist: aliyun-python-sdk-kms
Requires-Dist: asyncio-oss
Requires-Dist: attrs
Requires-Dist: certifi
Requires-Dist: cffi
Requires-Dist: charset-normalizer
Requires-Dist: crcmod
Requires-Dist: cryptography
Requires-Dist: frozenlist
Requires-Dist: idna
Requires-Dist: jmespath
Requires-Dist: multidict
Requires-Dist: oss2
Requires-Dist: propcache
Requires-Dist: pycparser
Requires-Dist: pycryptodome
Requires-Dist: requests
Requires-Dist: six
Requires-Dist: tqdm
Requires-Dist: urllib3
Requires-Dist: yarl
Requires-Dist: alibabacloud-oss-v2
